{
    "task": "В адресном поле командного слова содержатся только младшие разряды адресуемой ячейки. Дополнительный указательный регистр.\n<<<Адресация с регистром страницы является примером сокращённой адресации. При этом вся память разбивается на блоки-страницы. Размер страницы диктуется длиной адресного поля.>>>",
    "correct": [
        [
            "Адресация с регистром страницы является примером сокращённой адресации. При этом вся память разбивается на блоки-страницы. Размер страницы диктуется длиной адресного поля."
        ]
    ],
    "wrong": [],
    "meta": {
        "type": "ul",
        "link": "https://ru.wikipedia.org/wiki/Адресация_памяти"
    }
}