{
    "task": "Увеличение производительности суперскалярных процессоров ограничивается следующими факторами:\n<<<степенью внутреннего параллелизма инструкций;\nсложностью поиска зависимостей между инструкциями и затратами времени на этот поиск; сложностью схемы переименования регистров и затратами времени на переименование;\nобработкой инструкций ветвления.>>>",
    "correct": [
        [
            "степенью внутреннего параллелизма инструкций;",
            "сложностью поиска зависимостей между инструкциями и затратами времени на этот поиск; сложностью схемы переименования регистров и затратами времени на переименование;",
            "обработкой инструкций ветвления."
        ]
    ],
    "wrong": [],
    "meta": {
        "type": "ul",
        "link": "https://ru.wikipedia.org/wiki/Суперскалярность"
    }
}