{
    "task": "Основные качества, отличающие интернет-планшет от планшетного ПК:\n<<<низкая стоимость ;\nсенсорный экран для работы при помощи пальцев;\nупрощённый пользовательский интерфейс ;\nразвитые средства беспроводного интернет-соединения ;\nдлительное время автономной работы, которым ранее могли похвастаться лишь сотовые телефоны;\nзащищённость от хакерских атак.>>>",
    "correct": [
        [
            "низкая стоимость ;",
            "сенсорный экран для работы при помощи пальцев;",
            "упрощённый пользовательский интерфейс ;",
            "развитые средства беспроводного интернет-соединения ;",
            "длительное время автономной работы, которым ранее могли похвастаться лишь сотовые телефоны;",
            "защищённость от хакерских атак."
        ]
    ],
    "wrong": [],
    "meta": {
        "type": "ul",
        "link": "https://ru.wikipedia.org/wiki/Планшетный_компьютер"
    }
}