{
    "task": "Кроссплатформенность  —<<< способность программного обеспечения работать с несколькими аппаратными платформами или операционными системами. Обеспечивается благодаря использованию высокоуровневых языков программирования, сред разработки и выполнения, поддерживающих условную компиляцию, компоновку и выполнение кода для различных платформ. Типичным примером является программное обеспечение, предназначенное для работы в операционных системах Linux и Windows одновременно.>>>",
    "correct": [
        "способность программного обеспечения работать с несколькими аппаратными платформами или операционными системами. Обеспечивается благодаря использованию высокоуровневых языков программирования, сред разработки и выполнения, поддерживающих условную компиляцию, компоновку и выполнение кода для различных платформ. Типичным примером является программное обеспечение, предназначенное для работы в операционных системах Linux и Windows одновременно."
    ],
    "wrong": [],
    "meta": {
        "type": "definition"
    }
}