{
    "task": "Биоме́трия   —<<< автоматическое распознавание индивидов, основанное на их поведенческих и биологических характеристиках. Термин индивид в рамках автоматического распознавания относится только к человеку. Прикладное использование биометрии для автоматического распознавания — частный случай биометрии как биологической статистики. Термин биометрия в области физической и информационной безопасности стал использоваться в 1980-х гг., в 1970-х гг. использовался термин автоматическая идентификация личности.>>>",
    "correct": [
        "автоматическое распознавание индивидов, основанное на их поведенческих и биологических характеристиках. Термин индивид в рамках автоматического распознавания относится только к человеку. Прикладное использование биометрии для автоматического распознавания — частный случай биометрии как биологической статистики. Термин биометрия в области физической и информационной безопасности стал использоваться в 1980-х гг., в 1970-х гг. использовался термин автоматическая идентификация личности."
    ],
    "wrong": [],
    "meta": {
        "type": "definition"
    }
}